modbus_solar/__init__.py
modbus_solar/__main__.py
modbus_solar/cli.py
modbus_solar/get.py
modbus_solar-1.0.3.dist-info/METADATA
modbus_solar-1.0.3.dist-info/WHEEL
modbus_solar-1.0.3.dist-info/entry_points.txt
modbus_solar-1.0.3.dist-info/licenses/LICENSE
modbus_solar-1.0.3.dist-info/RECORD
