Metadata-Version: 2.4
Name: modbus_solar
Version: 1.0.3
Summary: A small package to pull stats from a Renogy Solar Charge Controller
Project-URL: Homepage, https://gitlab.com/boopzz/modbus-solar
Project-URL: Issues, https://gitlab.com/boopzz/modbus-solar/issues
Author-email: boopzz <boopzz@pm.me>
License: MIT
License-File: LICENSE
Keywords: modbus,renogy,solar
Classifier: License :: OSI Approved :: MIT License
Classifier: Operating System :: OS Independent
Classifier: Programming Language :: Python :: 3
Requires-Python: >=3.8
Requires-Dist: minimalmodbus>=2.0.0
Requires-Dist: typer
